minimal_csv_diff/__init__.py
minimal_csv_diff/api.py
minimal_csv_diff/cli.py
minimal_csv_diff/csv_processor.py
minimal_csv_diff/diff_engine.py
minimal_csv_diff/eda_analyzer.py
minimal_csv_diff/main.py
minimal_csv_diff-0.4.1.dist-info/METADATA
minimal_csv_diff-0.4.1.dist-info/WHEEL
minimal_csv_diff-0.4.1.dist-info/entry_points.txt
minimal_csv_diff-0.4.1.dist-info/top_level.txt
minimal_csv_diff-0.4.1.dist-info/RECORD
