Metadata-Version: 2.4
Name: minimal-csv-diff
Version: 0.4.1
Summary: Minimal tool to compare CSV files and generate diff reports
Author-email: luutuankiet <luutuankiet.ftu2@gmail.com>
Project-URL: Homepage, https://github.com/joon-solutions/minimal-csv-diff
Project-URL: Repository, https://github.com/joon-solutions/minimal-csv-diff
Requires-Python: >=3.10
Requires-Dist: chardet>=5.2.0
Requires-Dist: pandas>=2.0.0
Requires-Dist: polars>=1.31.0
Requires-Dist: psutil>=7.0.0
Requires-Dist: pytest>=8.3.5
Requires-Dist: unidecode>=1.4.0
